{"cameraMode":{"drawMode":0,"name":"Shaded","section":"Shading Mode"},"sceneLighting":false,"audioPlay":false,"sceneViewState":{"m_AlwaysRefresh":false,"showFog":true,"showSkybox":false,"showFlares":true,"showImageEffects":true,"showParticleSystems":true,"showVisualEffectGraphs":true,"m_FxEnabled":true},"in2DMode":false,"pivot":{"x":11.0,"y":0.0,"z":0.0},"rotation":{"x":0.02989404834806919,"y":-0.943709671497345,"z":0.08826520293951035,"w":0.31773799657821658},"size":1.545243740081787,"orthographic":false}